{
  "Лукойл": "logos/лукойл.png",
  "Газпромнефть": "logos/газпромнефть.png",
  "ЕКА": "logos/ека.png",
  "Shell": "logos/shell.png",
  "Шоколадница": "logos/шоколадница.png",
  "Му-Му": "logos/муму.png",
  "Osteria Mario": "logos/osteriamario.png",
  "Альма": "logos/альма.png",
  "KFC": "logos/kfc.png",
  "Burger King": "logos/burgerking.png",
  "Starbucks": "logos/starbucks.png",
  "Спортмастер": "logos/спортмастер.png",
  "Триал-Спорт": "logos/триалспорт.png",
  "ВелоСтрана": "logos/велострана.png",
  "Кант": "logos/кант.png",
  "Forward": "logos/forward.png",
  "Спорт Депо": "logos/спортдепо.png",
  "Формула Кино": "logos/формулакино.png",
  "Каро": "logos/каро.png",
  "Синема Парк": "logos/синемапарк.png",
  "Центральный Детский Мир": "logos/центральныйдетскиймир.png",
  "Каток ВДНХ": "logos/катоквднх.png",
  "Мосгорпарк": "logos/мосгорпарк.png"
}